mali/__init__.py
malipkghehe-0.1.2.dist-info/METADATA
malipkghehe-0.1.2.dist-info/WHEEL
malipkghehe-0.1.2.dist-info/top_level.txt
malipkghehe-0.1.2.dist-info/RECORD
