Metadata-Version: 2.4
Name: malipkghehe
Version: 0.1.2
Summary: Test auto-run with Discord webhook
Author: demo
Requires-Dist: requests
Dynamic: author
Dynamic: requires-dist
Dynamic: summary
